README.rst
setup.py
src/gocept/__init__.py
src/gocept.fssyncz2.egg-info/PKG-INFO
src/gocept.fssyncz2.egg-info/SOURCES.txt
src/gocept.fssyncz2.egg-info/dependency_links.txt
src/gocept.fssyncz2.egg-info/entry_points.txt
src/gocept.fssyncz2.egg-info/namespace_packages.txt
src/gocept.fssyncz2.egg-info/not-zip-safe
src/gocept.fssyncz2.egg-info/requires.txt
src/gocept.fssyncz2.egg-info/top_level.txt
src/gocept/fssyncz2/__init__.py
src/gocept/fssyncz2/folder.py
src/gocept/fssyncz2/main.py
src/gocept/fssyncz2/pickle_.py
src/gocept/fssyncz2/pythonscript.py
src/gocept/fssyncz2/testing.py
src/gocept/fssyncz2/tests.py
src/gocept/fssyncz2/traversing.py